{"source_url": "http://www.zocalo.com.mx", "url": "http://www.zocalo.com.mx/new_site/articulo/tuvo-17-salidas-bomberos-y-proteccion-civil-en-fin-de-ano/", "title": "Tuvo 17 salidas bomberos y protecci\u00f3n civil en fin de a\u00f1o", "top_image": "https://www.zocalo.com.mx/images/uploads/articles/salidas.jpg", "meta_img": "https://www.zocalo.com.mx/images/uploads/articles/salidas.jpg", "images": ["http://www.zocalo.com.mx/images/sized/images/uploads/articles/fut-1592505943-650x450.jpg", "https://www.zocalo.com.mx/images/uploads/blog/cubrebocas-cuadrado.jpg", "http://www.zocalo.com.mx/images/sized/images/uploads/articles/abrir\u00e1n-1592427876-650x450.jpg", "https://www.zocalo.com.mx/images/member_photos/photo_86.jpg", "http://www.zocalo.com.mx/images/skin/images/rs_android.png", "http://www.zocalo.com.mx/images/sized/images/uploads/articles/lesionado-1592495424-650x450.jpg", "https://www.zocalo.com.mx/images/rs_facebook.png", "https://www.zocalo.com.mx/images/uploads/articles/salidas.jpg", "https://www.zocalo.com.mx/images/site/icon-print.jpg", "http://www.zocalo.com.mx/images/sized/images/uploads/articles/indigenas-1592442607-650x450.jpg", "https://www.zocalo.com.mx/images/member_photos/photo_213.jpg", "https://www.zocalo.com.mx/images/member_photos/photo_129.jpg", "https://www.zocalo.com.mx/images/rs_twitter.png", "http://www.zocalo.com.mx/images/super-channel12-new.png", "https://www.zocalo.com.mx/images/member_photos/photo_56.jpg", "http://www.zocalo.com.mx/images/skin/images/rs_youtube.png", "https://www.zocalo.com.mx/images/member_photos/photo_1687.jpg", "https://www.zocalo.com.mx/images/rs_instagram.png", "https://www.zocalo.com.mx/images/uploads/blog/PN_19_22_junio.jpg", "https://www.zocalo.com.mx/images/member_photos/photo_1550.jpg", "https://www.zocalo.com.mx/images/member_photos/photo_216.jpg", "https://www.zocalo.com.mx/images/uploads/blog/PN_19_22_junio_2.jpg", "http://www.zocalo.com.mx/images/skin/images/rs_facebook.png", "http://www.zocalo.com.mx/images/sized/images/uploads/articles/bn-1592467265-650x450.jpg", "http://www.zocalo.com.mx/images/skin/images/rs_apple.png", "http://www.zocalo.com.mx/images/sized/images/uploads/articles/librop-1592468577-650x450.jpg", "http://www.zocalo.com.mx/images/skin/images/rs_instagram.png", "https://www.zocalo.com.mx/images/member_photos/photo_160.jpg", "http://www.zocalo.com.mx/images/sized/images/uploads/articles/salidas-621x354.jpg", "http://www.zocalo.com.mx/images/skin/images/home.png", "http://www.zocalo.com.mx/images/sized/images/uploads/articles/vuelvepenal-650x450.jpg", "https://www.zocalo.com.mx/?ACT=47&t=1&i=1662822", "https://www.zocalo.com.mx/images/member_photos/photo_1723.gif", "http://www.zocalo.com.mx/images/skin/images/radio-zocalo.png", "http://www.zocalo.com.mx/images/sized/images/uploads/articles/bancos-1592515627-650x450.jpg", "https://www.zocalo.com.mx/images/rs_youtube.png", "https://zocalo.com.mx/images/skin/images/logo-zocalo-mob.png", "http://www.zocalo.com.mx/images/sized/images/uploads/articles/alcalde-1592514400-650x450.jpg", "https://www.zocalo.com.mx/images/skin/images/ftr-logo.png", "http://www.zocalo.com.mx/images/skin/images/rs_twitter.png", "http://www.zocalo.com.mx/images/skin/images/logo-zocalo.png", "https://www.zocalo.com.mx/images/uploads/blog/compara.jpg", "https://zocalo.com.mx/images/skin/images/mobile-search.png"], "movies": [], "text": "Escuchar Nota\n\nPiedras Negras, Coah.- Fueron 17 salidas que realiz\u00f3 el Cuerpo de Bomberos y Protecci\u00f3n Civil a igual n\u00famero de destinos en los que fue necesaria la intervenci\u00f3n de los elementos durante fin de a\u00f1o, inform\u00f3 el director de dichas dependencias, Sergio Balbuena.\n\n\n\nExplic\u00f3 que 16 salidas fueron concretamente en atenci\u00f3n a incendios en zacatales, atribuidas todas a la quema de pirotecnia que si bien precis\u00f3, no fue tanta la poblaci\u00f3n que lo hizo, caus\u00f3 estos movimientos de la corporaci\u00f3n.\n\n\n\nSe\u00f1al\u00f3 que todos estos reportes fueron atendidos en tiempo y forma ya que el personal, tal como se hab\u00eda dado a conocer con anterioridad, no tuvieron descansos para este fin. \u201cEstuvimos muy activos, tuvimos un d\u00eda muy ajetreado\u201d, expres\u00f3.\n\n\n\nUn incendio m\u00e1s se registr\u00f3 en la colonia Acoros sobre la calle Olmos n\u00famero 2516, el cual consider\u00f3 de m\u00e1s importancia ya que fue provocado por un cortocircuito; \u201chubo necesidad de desalojar el domicilio adjunto el 2518 porque hab\u00eda mucho humo y los evacuamos\u201d, asever\u00f3.\n\n\n\nBalbuena indic\u00f3 que entre los casos de los zacatales se encontraron con pr\u00e1cticas que hace algunos a\u00f1os ya no se hac\u00eda, como es el tema de la quema de llantas sobre la calle Nezahualc\u00f3yotl muy cerca de la avenida Reforma.\n\n\n\nEl funcionario indic\u00f3 que ya se espera que se restablezcan las salidas del Cuerpo de Bomberos y Protecci\u00f3n Civil, pues es en diciembre cuando se ve un ligero incremento de atenciones en la ciudad.", "keywords": [], "meta_keywords": [""], "tags": [], "authors": [], "publish_date": null, "summary": "", "article_html": "", "meta_description": "", "meta_lang": "", "meta_favicon": "", "meta_data": {"fb": {"app_id": 1049160098509393, "pages": 59601464955}, "og": {"description": "El departamento de Bomberos mantuvo un fin de a\u00f1o muy activo en cuesti\u00f3n de trabajo - 02/01/2020", "title": "Tuvo 17 salidas bomberos y protecci\u00f3n civil en fin de a\u00f1o", "type": "website", "url": "https://www.zocalo.com.mx/new_site/articulo/tuvo-17-salidas-bomberos-y-proteccion-civil-en-fin-de-ano", "image": {"identifier": "https://www.zocalo.com.mx/images/uploads/articles/salidas.jpg", "width": 932, "height": 588}}, "twitter": {"card": "summary_large_image", "creator": {"identifier": "@PeriodicoZocalo", "id": "@PeriodicoZocalo"}, "title": "Tuvo 17 salidas bomberos y protecci\u00f3n civil en fin de a\u00f1o", "url": "https://www.zocalo.com.mx/new_site/articulo/tuvo-17-salidas-bomberos-y-proteccion-civil-en-fin-de-ano", "description": "El departamento de Bomberos mantuvo un fin de a\u00f1o muy activo en cuesti\u00f3n de trabajo", "image": "https://www.zocalo.com.mx/images/uploads/articles/salidas.jpg"}, "viewport": "width=device-width,minimum-scale=1.0,maximum-scale=1.0,user-scalable=no"}, "canonical_link": "https://www.zocalo.com.mx/new_site/articulo/tuvo-17-salidas-bomberos-y-proteccion-civil-en-fin-de-ano"}