{"source_url": "https://www.ots.at", "url": "https://www.ots.at/presseaussendung/OTS_20200310_OTS0021/gewessler-kuendigt-fortfuehrung-des-raus-aus-dem-oel-bonus-an", "title": "Gewessler k\u00fcndigt Fortf\u00fchrung des \u201eRaus aus dem \u00d6l\u201c-Bonus\u2018 an", "top_image": "https://static.ots.at/pressemappe/668/1194_fb.gif?t=1435157121", "meta_img": "https://static.ots.at/pressemappe/668/1194_fb.gif?t=1435157121", "images": ["https://static.ots.at//css/images/banner-apaCampus.jpg", "https://www.ots.at/anhang/2020/03/11/OBS/OBS_20200311_OBS0015_bildblock.jpg", "https://www.ots.at/anhang/2020/02/04/OVS/OVS_20200204_OVS0001_bildblock.jpg", "https://www.ots.at/anhang/2020/02/28/OVS/OVS_20200228_OVS0001_bildblock.jpg", "https://www.ots.at/anhang/2020/03/06/OBS/OBS_20200306_OBS0022_bildblock.jpg", "https://www.ots.at/anhang/2020/03/05/OVS/OVS_20200305_OVS0002_bildblock.jpg", "https://static.ots.at//images/erhaltlich-im-app-store.png", "https://www.ots.at/anhang/2020/01/23/OVS/OVS_20200123_OVS0003_bildblock.jpg", "https://www.ots.at/anhang/2020/02/26/OVS/OVS_20200226_OVS0001_bildblock.jpg", "https://www.ots.at/anhang/2020/03/09/OBS/OBS_20200309_OBS0032_bildblock.jpg", "https://www.ots.at/anhang/2020/03/09/OBS/OBS_20200309_OBS0001_bildblock.jpg", "https://www.ots.at/anhang/2020/03/05/OVS/OVS_20200305_OVS0001_bildblock.jpg", "https://www.ots.at/anhang/2020/03/06/OVS/OVS_20200306_OVS0001_bildblock.jpg", "https://www.ots.at/anhang/2020/03/09/OBS/OBS_20200309_OBS0003_bildblock.jpg", "https://www.ots.at/anhang/2020/03/06/OBS/OBS_20200306_OBS0029_bildblock.jpg", "https://static.ots.at//css/images/banner-mailabo.jpg", "https://www.ots.at/anhang/2020/03/09/OBS/OBS_20200309_OBS0002_bildblock.jpg", "https://www.ots.at/anhang/2020/02/03/OVS/OVS_20200203_OVS0001_bildblock.jpg", "https://static.ots.at/css/images/blank.png", "https://www.ots.at/anhang/2020/02/27/OVS/OVS_20200227_OVS0001_bildblock.jpg", "https://www.ots.at/anhang/2020/03/05/OBS/OBS_20200305_OBS0041_bildblock.jpg", "https://www.ots.at/anhang/2020/03/05/OBS/OBS_20200305_OBS0036_bildblock.jpg", "https://static.ots.at/pressemappe/668/1194_fb.gif?t=1435157121", "https://www.ots.at/anhang/2020/01/28/OVS/OVS_20200128_OVS0001_bildblock.jpg", "https://www.ots.at/anhang/2020/03/05/OBS/OBS_20200305_OBS0040_bildblock.jpg", "https://static.ots.at//css/images/banner-twitterlist.jpg", "https://static.ots.at//images/jetzt-bei-google-play.png"], "movies": [], "text": "Gewessler k\u00fcndigt Fortf\u00fchrung des \u201eRaus aus dem \u00d6l\u201c-Bonus\u2018 an\n\nDetails folgen nach Budgetbeschluss \u2013 Gr\u00fcne Handschrift soll sichtbar werden\n\nWien (OTS) - Bundesministerin Leonore Gewessler k\u00fcndigte die Fortf\u00fchrung des \u201eRaus aus dem \u00d6l\u201c-Bonus\u2018 im Rahmen der Er\u00f6ffnung der Energiesparmesse Wels am 6. M\u00e4rz an. Dieser soll mit dem Budgetbeschluss am 18. M\u00e4rz reaktiviert werden und auch r\u00fcckwirkend gelten. Detaillierte Informationen sollen folgen \u2013 insbesondere das F\u00f6rdervolumen. Dazu meinte Gewessler nur, dass die gr\u00fcne Handschrift bei der F\u00f6rderung sichtbar sein wird. Der \u00d6sterreichische Biomasse-Verband begr\u00fc\u00dft die Fortsetzung des Zuschusses, der als wichtiges Signal f\u00fcr die Konsumenten, aber auch f\u00fcr Kesselhersteller gilt. \u201eEine Kontinuit\u00e4t bei der F\u00f6rderung ist sehr wichtig, damit sich alle Beteiligten auch darauf einstellen k\u00f6nnen\u201c, erkl\u00e4rt Franz Titschenbacher, Pr\u00e4sident des \u00d6sterreichischen Biomasse-Verbandes. Nunmehr gilt es, die Regierungspl\u00e4ne umzusetzen: Das Verbot von \u00d6lheizungen bei Heizungswechsel ab 2021, der verpflichtende Austausch von \u00d6lkesseln \u00e4lter als 25 Jahre ab 2025 und der Austausch aller Kessel bis 2035. Der Einbau von \u00d6lkesseln im Neubau ist bereits seit Jahresbeginn verboten.\n\nInfos zum \u201eRaus aus dem \u00d6l\u201c-Bonus\n\nIm Vorjahr wurde der Tausch eines fossilen Kessels auf ein erneuerbares Energiesystem vom Bund mit bis zu 5.000 Euro unterst\u00fctzt. Die bereitgestellten 42,6 Millionen Euro wurden aber bereits im Juni aufgrund der hohen Nachfrage ausgesch\u00f6pft. Im Herbst wurde auch die zweite Tranche von zus\u00e4tzlichen 20 Millionen Euro innerhalb weniger Wochen abgeholt.\n\nR\u00fcckfragen & Kontakt:\n\n\u00d6sterreichischer Biomasse-Verband\n\nAntonio Fuljetic-Kristan\n\n+43 (0)1 533 07 97 \u2013 31, 0660 855 6804\n\nfuljetic @ biomasseverband.at", "keywords": [], "meta_keywords": ["Agrar", "Energiemarkt", "Energiequellen", "Klima", "Bundesregierung", "Presseaussendung", "Pressemitteilung", "APA", "OTS", "APA-OTS"], "tags": [], "authors": [], "publish_date": null, "summary": "", "article_html": "", "meta_description": "Details folgen nach Budgetbeschluss \u2013 Gr\u00fcne Handschrift soll sichtbar werden", "meta_lang": "de", "meta_favicon": "https://www.ots.at/favicon.ico", "meta_data": {"verify-v1": "Dfn4kJa3IdV+8gsygdvfipSA6IqmpsYL1FpvK2dJp6Q=", "viewport": "width=device-width, initial-scale=1, minimum-scale=1, user-scalable=yes", "apple-itunes-app": "app-id=360706674", "description": "Details folgen nach Budgetbeschluss \u2013 Gr\u00fcne Handschrift soll sichtbar werden", "keywords": "Agrar, Energiemarkt, Energiequellen, Klima, Bundesregierung, Presseaussendung, Pressemitteilung, APA, OTS, APA-OTS", "robots": "max-snippet:-1, max-image-preview:standard, max-video-preview:-1", "fb": {"admins": 100000800184779, "pages": 113528797561}, "twitter": {"card": "summary", "image": "https://static.ots.at/pressemappe/668/1194_fb.gif?t=1435157121", "site": "@apaots", "url": "https://www.ots.at/presseaussendung/OTS_20200310_OTS0021/gewessler-kuendigt-fortfuehrung-des-raus-aus-dem-oel-bonus-an", "title": "Gewessler k\u00fcndigt Fortf\u00fchrung des \u201eRaus aus dem \u00d6l\u201c-Bonus\u2018 an", "description": "Details folgen nach Budgetbeschluss \u2013 Gr\u00fcne Handschrift soll sichtbar werden"}, "og": {"site_name": "OTS.at", "title": "Gewessler k\u00fcndigt Fortf\u00fchrung des \u201eRaus aus dem \u00d6l\u201c-Bonus\u2018 an", "description": "Details folgen nach Budgetbeschluss \u2013 Gr\u00fcne Handschrift soll sichtbar werden", "url": "https://www.ots.at/presseaussendung/OTS_20200310_OTS0021/gewessler-kuendigt-fortfuehrung-des-raus-aus-dem-oel-bonus-an", "type": "article", "image": {"identifier": "https://static.ots.at/pressemappe/668/1194_fb.gif?t=1435157121", "width": 250, "height": 250, "type": "image/gif"}}, "as": {"channel": "Wirtschaft"}}, "canonical_link": "https://www.ots.at/presseaussendung/OTS_20200310_OTS0021/gewessler-kuendigt-fortfuehrung-des-raus-aus-dem-oel-bonus-an"}