{"source_url": "https://www.yenicaggazetesi.com.tr", "url": "https://www.yenicaggazetesi.com.tr/altin-alacaklar-dikkat-uzmanlardan-kritik-tahmin-282064h.htm", "title": "Alt\u0131n alacaklar dikkat! Uzmanlardan kritik tahmin", "top_image": "https://cdn.yenicaggazetesi.com.tr/news/392110.jpg", "meta_img": "https://cdn.yenicaggazetesi.com.tr/news/392110.jpg", "images": ["https://www.yenicaggazetesi.com.tr/s/i/img-rep.gif", "https://cdn.yenicaggazetesi.com.tr/news/399092.jpg", "https://cdn.yenicaggazetesi.com.tr/news/392110.jpg", "https://cdn.yenicaggazetesi.com.tr/news/399126.jpg", "https://www.yenicaggazetesi.com.tr/d/banner/2611DOK01_2018.gif", "https://cdn.yenicaggazetesi.com.tr/gallery/5067_1.jpg", "https://www.yenicaggazetesi.com.tr/s/i/1x1.gif", "https://cdn.yenicaggazetesi.com.tr/news/399000.jpg", "https://www.yenicaggazetesi.com.tr/d/other/sar.jpg", "https://cdn.yenicaggazetesi.com.tr/news_t/398559.jpg", "https://cdn.yenicaggazetesi.com.tr/news/399110.jpg", "https://cdn.yenicaggazetesi.com.tr/news/399066.jpg", "https://cdn.yenicaggazetesi.com.tr/news/399100.jpg", "https://cdn.yenicaggazetesi.com.tr/news/399104.jpg", "https://www.yenicaggazetesi.com.tr/d/banner/261101GUN_2018.gif", "https://cdn.yenicaggazetesi.com.tr/news/399111.jpg", "https://www.yenicaggazetesi.com.tr/s/i/logo.png", "https://cdn.yenicaggazetesi.com.tr/news/399099.jpg", "https://www.yenicaggazetesi.com.tr/d/other/c1-020.jpg", "https://cdn.yenicaggazetesi.com.tr/news/399106.jpg", "https://www.yenicaggazetesi.com.tr/d/birincisayfa/2106YC01_2019.gif", "https://www.yenicaggazetesi.com.tr/d/other/gunboyu-kutu-017.png"], "movies": [], "text": "Alt\u0131n\u0131n gram fiyat\u0131, g\u00fcne d\u00fc\u015f\u00fc\u015fle ba\u015flamas\u0131n\u0131n ard\u0131ndan 378 liradan i\u015flem g\u00f6r\u00fcyor. Analistler, teknik a\u00e7\u0131dan alt\u0131n\u0131n ons fiyat\u0131nda 1.730 dolar\u0131n destek 1.750 dolar\u0131n diren\u00e7 olarak \u00f6ne \u00e7\u0131kt\u0131\u011f\u0131n\u0131, gram alt\u0131nda ise 380-390 lira band\u0131n\u0131n izlenece\u011fini s\u00f6yledi.\n\nYeni g\u00fcne de\u011fer kayb\u0131yla ba\u015flayan alt\u0131n\u0131n gram fiyat\u0131, 378 lira seviyesinde seyrediyor. Ayn\u0131 dakikalarda \u00e7eyrek alt\u0131n 626 lira, Cumhuriyet alt\u0131n\u0131 da 2.494 liradan sat\u0131l\u0131yor.\n\n\n\nAlt\u0131n\u0131n ons fiyat\u0131, \u015fu dakikalarda \u00f6nceki kapan\u0131\u015fa g\u00f6re y\u00fczde 0,2 de\u011fer kayb\u0131yla 1.740 dolar seviyesinde bulunuyor.\n\n\n\nAnalistler, ABD ile \u00c7in aras\u0131nda artan gerilime ra\u011fmen, d\u00fcn d\u00fcnya genelinde a\u00e7\u0131klanan imalat sanayi Sat\u0131nalma Y\u00f6neticileri Endeksi (PMI) verilerinin beklentilerden iyi gelmesiyle risk i\u015ftah\u0131n\u0131n g\u00f6rece artt\u0131\u011f\u0131n\u0131, bu durumun da alt\u0131n\u0131n ons fiyat\u0131n\u0131 a\u015fa\u011f\u0131 y\u00f6nl\u00fc bask\u0131lad\u0131\u011f\u0131n\u0131 kaydetti.\n\n\n\nBug\u00fcn veri takviminin zay\u0131f oldu\u011funu kaydeden analistler, ABD'de siyahi George Floyd'un polis \u015fiddeti sonucu hayat\u0131n\u0131 kaybetmesinin ard\u0131ndan devam eden g\u00f6sterilere ili\u015fkin haber ak\u0131\u015f\u0131n\u0131n takip edilece\u011fini bildirdi.\n\n\n\nAnalistler, teknik a\u00e7\u0131dan alt\u0131n\u0131n ons fiyat\u0131nda 1.730 dolar\u0131n destek 1.750 dolar\u0131n diren\u00e7 olarak \u00f6ne \u00e7\u0131kt\u0131\u011f\u0131n\u0131, gram alt\u0131nda ise 380-390 lira band\u0131n\u0131n izlenece\u011fini s\u00f6yledi.", "keywords": [], "meta_keywords": ["alt\u0131n", "ons", "\u00e7eyrek alt\u0131n", "cumhuriyet alt\u0131n\u0131", "gram alt\u0131n"], "tags": ["cumhuriyet alt\u0131n\u0131", "\u00e7eyrek alt\u0131n", "alt\u0131n", "gram alt\u0131n", "ons"], "authors": ["Yeni \u00c7a\u011f Gazetesi"], "publish_date": null, "summary": "", "article_html": "", "meta_description": "Alt\u0131n\u0131n gram fiyat\u0131, g\u00fcne d\u00fc\u015f\u00fc\u015fle ba\u015flamas\u0131n\u0131n ard\u0131ndan 378 liradan i\u015flem g\u00f6r\u00fcyor. Analistler, teknik a\u00e7\u0131dan alt\u0131n\u0131n ons fiyat\u0131nda 1.730 dolar\u0131n destek 1.750 dolar\u0131n diren\u00e7 olarak \u00f6ne \u00e7\u0131kt\u0131\u011f\u0131n\u0131, gram alt\u0131nda ise 380-390 lira band\u0131n\u0131n izlenece\u011fini s\u00f6yledi.", "meta_lang": "tr", "meta_favicon": "/s/assets/favicon/apple-touch-icon.png", "meta_data": {"keywords": "alt\u0131n, ons, \u00e7eyrek alt\u0131n, cumhuriyet alt\u0131n\u0131, gram alt\u0131n", "description": "Alt\u0131n\u0131n gram fiyat\u0131, g\u00fcne d\u00fc\u015f\u00fc\u015fle ba\u015flamas\u0131n\u0131n ard\u0131ndan 378 liradan i\u015flem g\u00f6r\u00fcyor. Analistler, teknik a\u00e7\u0131dan alt\u0131n\u0131n ons fiyat\u0131nda 1.730 dolar\u0131n destek 1.750 dolar\u0131n diren\u00e7 olarak \u00f6ne \u00e7\u0131kt\u0131\u011f\u0131n\u0131, gram alt\u0131nda ise 380-390 lira band\u0131n\u0131n izlenece\u011fini s\u00f6yledi.", "fb": {"app_id": 465402641026108}, "DC.date.issued": "2020-06-02T15:59:53+03:00", "news_keywords": "alt\u0131n, ons, \u00e7eyrek alt\u0131n, cumhuriyet alt\u0131n\u0131, gram alt\u0131n", "og": {"type": "article", "site_name": "Yeni \u00c7a\u011f Gazetesi", "url": "https://www.yenicaggazetesi.com.tr/altin-alacaklar-dikkat-uzmanlardan-kritik-tahmin-282064h.htm", "title": "Alt\u0131n alacaklar dikkat! Uzmanlardan kritik tahmin", "description": "Alt\u0131n\u0131n gram fiyat\u0131, g\u00fcne d\u00fc\u015f\u00fc\u015fle ba\u015flamas\u0131n\u0131n ard\u0131ndan 378 liradan i\u015flem g\u00f6r\u00fcyor. Analistler, teknik a\u00e7\u0131dan alt\u0131n\u0131n ons fiyat\u0131nda 1.730 dolar\u0131n destek 1.750 dolar\u0131n diren\u00e7 olarak \u00f6ne \u00e7\u0131kt\u0131\u011f\u0131n\u0131, gram alt\u0131nda ise 380-390 lira band\u0131n\u0131n izlenece\u011fini s\u00f6yledi.", "image": {"identifier": "https://cdn.yenicaggazetesi.com.tr/news/392110.jpg", "width": 980, "height": 360}}, "twitter": {"card": "summary_large_image", "site": "@Gazete_Yenicag", "url": "https://www.yenicaggazetesi.com.tr/altin-alacaklar-dikkat-uzmanlardan-kritik-tahmin-282064h.htm", "title": "Alt\u0131n alacaklar dikkat! Uzmanlardan kritik tahmin", "description": "Alt\u0131n\u0131n gram fiyat\u0131, g\u00fcne d\u00fc\u015f\u00fc\u015fle ba\u015flamas\u0131n\u0131n ard\u0131ndan 378 liradan i\u015flem g\u00f6r\u00fcyor. Analistler, teknik a\u00e7\u0131dan alt\u0131n\u0131n ons fiyat\u0131nda 1.730 dolar\u0131n destek 1.750 dolar\u0131n diren\u00e7 olarak \u00f6ne \u00e7\u0131kt\u0131\u011f\u0131n\u0131, gram alt\u0131nda ise 380-390 lira band\u0131n\u0131n izlenece\u011fini s\u00f6yledi.", "image": "https://cdn.yenicaggazetesi.com.tr/news/392110.jpg"}, "msapplication-TileColor": "#ffffff", "msapplication-config": "/s/assets/favicon/browserconfig.xml", "theme-color": "#ffffff"}, "canonical_link": "https://www.yenicaggazetesi.com.tr/altin-alacaklar-dikkat-uzmanlardan-kritik-tahmin-282064h.htm"}