{"source_url": "http://www.globenewswire.com", "url": "http://www.globenewswire.com/news-release/2020/05/22/2037721/0/en/VINCIT-PLC-SHARE-REPURCHASE-22-5-2020.html", "title": "VINCIT PLC SHARE REPURCHASE 22.5.2020", "top_image": "https://ml-eu.globenewswire.com/Resource/Download/12c3b4b2-6a87-4fdf-a79c-d19769f2e526?size=1", "meta_img": "https://ml-eu.globenewswire.com/Resource/Download/12c3b4b2-6a87-4fdf-a79c-d19769f2e526?size=1", "images": ["http://www.globenewswire.com/content/Images/thumbnail-icons/attachment/thumb-excel.png?v=1234", "https://ml-eu.globenewswire.com/Resource/Download/12c3b4b2-6a87-4fdf-a79c-d19769f2e526?size=1"], "movies": [], "text": "For more information, please contact:", "keywords": [], "meta_keywords": ["Helsinki Stock Exchange:VINCIT", "Vincit Oyj"], "tags": [], "authors": ["Vincit Oyj"], "publish_date": "Fri May 22 00:00:00 2020", "summary": "", "article_html": "", "meta_description": "VINCIT PLCANNOUNCEMENT22.5.2020\u00a0\u00a0\u00a0\u00a0\u00a0\u00a0VINCIT PLC SHARE REPURCHASE 22.5.2020\u00a0\u00a0\u00a0\u00a0In the Helsinki Stock Exchange\u00a0\u00a0\u00a0\u00a0\u00a0Trade date22.5.2020\u00a0Bourse...", "meta_lang": "en", "meta_favicon": "/Content/logo/favicon.ico", "meta_data": {"viewport": "width=device-width, initial-scale=1", "author": "Vincit Oyj", "keywords": "Helsinki Stock Exchange:VINCIT, Vincit Oyj", "description": "VINCIT PLCANNOUNCEMENT22.5.2020\u00a0\u00a0\u00a0\u00a0\u00a0\u00a0VINCIT PLC SHARE REPURCHASE 22.5.2020\u00a0\u00a0\u00a0\u00a0In the Helsinki Stock Exchange\u00a0\u00a0\u00a0\u00a0\u00a0Trade date22.5.2020\u00a0Bourse...", "title": "VINCIT PLC SHARE REPURCHASE 22.5.2020", "ticker": "Helsinki:VINCIT", "DC.date.issued": "5/22/2020", "google-site-verification": "TPh-fYpDjXZUz98ciWasVb52qbvctqomC6zZc8vuUPU", "original-source": "https://www.globenewswire.com/news-release/2020/05/22/2037721/0/en/VINCIT-PLC-SHARE-REPURCHASE-22-5-2020.html", "twitter": {"card": "summary", "site": "globenewswire", "title": "VINCIT PLC SHARE REPURCHASE 22.5.2020", "description": "VINCIT PLCANNOUNCEMENT22.5.2020\u00a0\u00a0\u00a0\u00a0\u00a0\u00a0VINCIT PLC SHARE REPURCHASE 22.5.2020\u00a0\u00a0\u00a0\u00a0In the Helsinki Stock Exchange\u00a0\u00a0\u00a0\u00a0\u00a0Trade date22.5.2020\u00a0Bourse...", "image": "https://ml-eu.globenewswire.com/Resource/Download/12c3b4b2-6a87-4fdf-a79c-d19769f2e526?size=1"}, "og": {"title": "VINCIT PLC SHARE REPURCHASE 22.5.2020", "type": "article", "image": "https://ml-eu.globenewswire.com/Resource/Download/12c3b4b2-6a87-4fdf-a79c-d19769f2e526?size=1", "url": "https://www.globenewswire.com/news-release/2020/05/22/2037721/0/en/VINCIT-PLC-SHARE-REPURCHASE-22-5-2020.html", "description": "VINCIT PLCANNOUNCEMENT22.5.2020\u00a0\u00a0\u00a0\u00a0\u00a0\u00a0VINCIT PLC SHARE REPURCHASE 22.5.2020\u00a0\u00a0\u00a0\u00a0In the Helsinki Stock Exchange\u00a0\u00a0\u00a0\u00a0\u00a0Trade date22.5.2020\u00a0Bourse...", "article": {"published_time": "5/22/2020 3:30:00 PM", "author": "Vincit Oyj", "tag": "Vincit Oyj,"}, "locale": "en_US", "site_name": "GlobeNewswire News Room"}}, "canonical_link": "https://www.globenewswire.com/news-release/2020/05/22/2037721/0/en/VINCIT-PLC-SHARE-REPURCHASE-22-5-2020.html"}